gramlib/__init__.py
gramlib/gram.py
gramlib/gram1.py
gramlib-3.0.1.dist-info/METADATA
gramlib-3.0.1.dist-info/WHEEL
gramlib-3.0.1.dist-info/top_level.txt
gramlib-3.0.1.dist-info/RECORD
