Metadata-Version: 2.2
Name: gramLib
Version: 3.0.1
Summary: libraly in create database in gram
Home-page: https://github.com/your_username/my_gram_library
Author: NEFOR
Author-email: gram@gmail.com
Classifier: Programming Language :: Python :: 3
Classifier: License :: OSI Approved :: MIT License
Classifier: Operating System :: OS Independent
Requires-Python: >=3.6
Dynamic: author
Dynamic: author-email
Dynamic: classifier
Dynamic: description
Dynamic: description-content-type
Dynamic: home-page
Dynamic: requires-python
Dynamic: summary
